astrapy/__init__.py
astrapy/admin/__init__.py
astrapy/admin/admin.py
astrapy/admin/endpoints.py
astrapy/api_options.py
astrapy/authentication.py
astrapy/client.py
astrapy/collection.py
astrapy/constants.py
astrapy/cursors.py
astrapy/data/__init__.py
astrapy/data/collection.py
astrapy/data/cursors/__init__.py
astrapy/data/cursors/cursor.py
astrapy/data/cursors/farr_cursor.py
astrapy/data/cursors/find_cursor.py
astrapy/data/cursors/query_engine.py
astrapy/data/cursors/reranked_result.py
astrapy/data/database.py
astrapy/data/info/collection_descriptor.py
astrapy/data/info/database_info.py
astrapy/data/info/reranking.py
astrapy/data/info/table_descriptor/table_altering.py
astrapy/data/info/table_descriptor/table_columns.py
astrapy/data/info/table_descriptor/table_creation.py
astrapy/data/info/table_descriptor/table_indexes.py
astrapy/data/info/table_descriptor/table_listing.py
astrapy/data/info/vectorize.py
astrapy/data/table.py
astrapy/data/utils/__init__.py
astrapy/data/utils/collection_converters.py
astrapy/data/utils/distinct_extractors.py
astrapy/data/utils/extended_json_converters.py
astrapy/data/utils/table_converters.py
astrapy/data/utils/table_types.py
astrapy/data/utils/vector_coercion.py
astrapy/data_types/__init__.py
astrapy/data_types/data_api_date.py
astrapy/data_types/data_api_duration.py
astrapy/data_types/data_api_map.py
astrapy/data_types/data_api_set.py
astrapy/data_types/data_api_time.py
astrapy/data_types/data_api_timestamp.py
astrapy/data_types/data_api_vector.py
astrapy/database.py
astrapy/exceptions/__init__.py
astrapy/exceptions/collection_exceptions.py
astrapy/exceptions/data_api_exceptions.py
astrapy/exceptions/devops_api_exceptions.py
astrapy/exceptions/table_exceptions.py
astrapy/ids.py
astrapy/info.py
astrapy/py.typed
astrapy/results.py
astrapy/settings/__init__.py
astrapy/settings/defaults.py
astrapy/settings/error_messages.py
astrapy/table.py
astrapy/utils/__init__.py
astrapy/utils/api_commander.py
astrapy/utils/api_options.py
astrapy-2.0.0.dist-info/LICENSE.md
astrapy-2.0.0.dist-info/METADATA
astrapy-2.0.0.dist-info/WHEEL
astrapy-2.0.0.dist-info/RECORD
