Metadata-Version: 2.1
Name: astrapy
Version: 2.0.0
Summary: AstraPy is a Pythonic SDK for DataStax Astra and its Data API
Author: Stefano Lottini
Author-email: stefano.lottini@datastax.com
Requires-Python: >=3.8.0,<4.0.0
Classifier: Programming Language :: Python :: 3
Classifier: Programming Language :: Python :: 3.8
Classifier: Programming Language :: Python :: 3.9
Classifier: Programming Language :: Python :: 3.10
Classifier: Programming Language :: Python :: 3.11
Requires-Dist: deprecation (>=2.1.0,<2.2.0)
Requires-Dist: httpx[http2] (>=0.25.2,<1)
Requires-Dist: pymongo (>=3)
Requires-Dist: toml (>=0.10.2,<0.11.0)
Requires-Dist: typing-extensions (>=4.0)
Requires-Dist: uuid6 (>=2024.1.12)
